CHANGES.txt
MANIFEST.in
README.rst
setup.py
nose_ittr/__init__.py
nose_ittr/ittr_multiplier.py
nose_ittr/setup_ittr.py
nose_ittr.egg-info/PKG-INFO
nose_ittr.egg-info/SOURCES.txt
nose_ittr.egg-info/dependency_links.txt
nose_ittr.egg-info/entry_points.txt
nose_ittr.egg-info/not-zip-safe
nose_ittr.egg-info/top_level.txt