Metadata-Version: 1.1
Name: nose-ittr
Version: 0.0.4
Summary: nose expansion for supporting parametrized testing
Home-page: https://github.com/taykey/nose-ittr
Author: Sergey Ragatsky
Author-email: serg@taykey.com
License: Apache Software License
Keywords: nose nosetest docstring metaclass parametrized testing plugin
Platform: any
Classifier: Programming Language :: Python
Classifier: Development Status :: 4 - Beta
Classifier: Natural Language :: English
Classifier: Environment :: Other Environment
Classifier: Intended Audience :: Developers
Classifier: License :: OSI Approved :: Apache Software License
Classifier: Operating System :: OS Independent
Classifier: Topic :: Software Development :: Libraries :: Python Modules
Classifier: Topic :: Software Development :: Libraries :: Application Frameworks
Classifier: Topic :: Software Development :: Testing
